etatime/__init__.py
etatime/constants.py
etatime/eta.py
etatime-3.5.4.dist-info/LICENSE
etatime-3.5.4.dist-info/WHEEL
etatime-3.5.4.dist-info/METADATA
etatime-3.5.4.dist-info/RECORD
