Metadata-Version: 2.1
Name: etatime
Version: 3.5.4
Summary: A library for tracking, computing, and formatting time estimates. (Based on `tqdm`).
Author-email: Ella Jameson <ellagjameson@gmail.com>
Requires-Python: >=3.10
Classifier: Development Status :: 5 - Production/Stable
Classifier: License :: OSI Approved :: GNU General Public License v3 or later (GPLv3+)
Classifier: Programming Language :: Python
Classifier: Programming Language :: Python :: 3
Classifier: Programming Language :: Python :: 3.10
Classifier: Programming Language :: Python :: 3.11
Classifier: Programming Language :: Python :: 3.12
Classifier: Programming Language :: Python :: 3 :: Only
Requires-Dist: timefmt >=1.0.0
Requires-Dist: tqdm >=4.66.1
Project-URL: documentation, https://etatime.readthedocs.io/en/latest/index.html
Project-URL: homepage, https://github.com/nimaid/python-etatime
Project-URL: issues, https://github.com/nimaid/python-etatime/issues
Project-URL: repository, https://github.com/nimaid/python-etatime
